{
    "images": [
        {
            "id": "79881",
            "file_path": "grefcoco_dataset/images/79881_original.png",
            "data_source": "https://huggingface.co/datasets/qixiangbupt/grefcoco",
            "height": 428,
            "width": 640,
            "scene": "",
            "is_longtail": false,
            "task": "referring_segmentation",
            "problem": "item behind boys right ear",
            "problem_type": {
                "num_class": "",
                "num_instance": ""
            }
        }
    ],
    "annotations": [
        {
            "id": 0,
            "image_id": "79881",
            "category_id": null,
            "bbox": null,
            "area": null,
            "shape_type": "polygon",
            "error_type": null,
            "iou": 0.7160150181253236,
            "segmentation": [
                [
                    [
                        398.0,
                        62.0
                    ],
                    [
                        397.0,
                        63.0
                    ],
                    [
                        394.0,
                        63.0
                    ],
                    [
                        393.0,
                        64.0
                    ],
                    [
                        389.0,
                        64.0
                    ],
                    [
                        388.0,
                        65.0
                    ],
                    [
                        385.0,
                        65.0
                    ],
                    [
                        384.0,
                        66.0
                    ],
                    [
                        383.0,
                        66.0
                    ],
                    [
                        381.0,
                        68.0
                    ],
                    [
                        381.0,
                        69.0
                    ],
                    [
                        379.0,
                        71.0
                    ],
                    [
                        379.0,
                        74.0
                    ],
                    [
                        378.0,
                        75.0
                    ],
                    [
                        376.0,
                        75.0
                    ],
                    [
                        376.0,
                        76.0
                    ],
                    [
                        375.0,
                        77.0
                    ],
                    [
                        375.0,
                        78.0
                    ],
                    [
                        372.0,
                        81.0
                    ],
                    [
                        371.0,
                        81.0
                    ],
                    [
                        371.0,
                        99.0
                    ],
                    [
                        370.0,
                        100.0
                    ],
                    [
                        370.0,
                        115.0
                    ],
                    [
                        369.0,
                        116.0
                    ],
                    [
                        369.0,
                        118.0
                    ],
                    [
                        367.0,
                        120.0
                    ],
                    [
                        367.0,
                        123.0
                    ],
                    [
                        368.0,
                        124.0
                    ],
                    [
                        368.0,
                        125.0
                    ],
                    [
                        369.0,
                        126.0
                    ],
                    [
                        367.0,
                        128.0
                    ],
                    [
                        367.0,
                        130.0
                    ],
                    [
                        366.0,
                        131.0
                    ],
                    [
                        366.0,
                        133.0
                    ],
                    [
                        365.0,
                        134.0
                    ],
                    [
                        365.0,
                        136.0
                    ],
                    [
                        364.0,
                        137.0
                    ],
                    [
                        364.0,
                        139.0
                    ],
                    [
                        362.0,
                        141.0
                    ],
                    [
                        362.0,
                        142.0
                    ],
                    [
                        361.0,
                        143.0
                    ],
                    [
                        361.0,
                        148.0
                    ],
                    [
                        360.0,
                        149.0
                    ],
                    [
                        360.0,
                        156.0
                    ],
                    [
                        359.0,
                        157.0
                    ],
                    [
                        359.0,
                        159.0
                    ],
                    [
                        358.0,
                        160.0
                    ],
                    [
                        358.0,
                        173.0
                    ],
                    [
                        359.0,
                        174.0
                    ],
                    [
                        359.0,
                        175.0
                    ],
                    [
                        360.0,
                        176.0
                    ],
                    [
                        360.0,
                        178.0
                    ],
                    [
                        361.0,
                        178.0
                    ],
                    [
                        362.0,
                        179.0
                    ],
                    [
                        366.0,
                        179.0
                    ],
                    [
                        367.0,
                        180.0
                    ],
                    [
                        368.0,
                        180.0
                    ],
                    [
                        370.0,
                        182.0
                    ],
                    [
                        370.0,
                        183.0
                    ],
                    [
                        373.0,
                        186.0
                    ],
                    [
                        373.0,
                        187.0
                    ],
                    [
                        374.0,
                        188.0
                    ],
                    [
                        376.0,
                        188.0
                    ],
                    [
                        380.0,
                        192.0
                    ],
                    [
                        380.0,
                        193.0
                    ],
                    [
                        381.0,
                        194.0
                    ],
                    [
                        382.0,
                        194.0
                    ],
                    [
                        383.0,
                        195.0
                    ],
                    [
                        384.0,
                        195.0
                    ],
                    [
                        387.0,
                        198.0
                    ],
                    [
                        390.0,
                        198.0
                    ],
                    [
                        391.0,
                        199.0
                    ],
                    [
                        393.0,
                        199.0
                    ],
                    [
                        396.0,
                        202.0
                    ],
                    [
                        397.0,
                        202.0
                    ],
                    [
                        400.0,
                        205.0
                    ],
                    [
                        400.0,
                        207.0
                    ],
                    [
                        402.0,
                        209.0
                    ],
                    [
                        403.0,
                        209.0
                    ],
                    [
                        405.0,
                        211.0
                    ],
                    [
                        405.0,
                        213.0
                    ],
                    [
                        406.0,
                        214.0
                    ],
                    [
                        407.0,
                        214.0
                    ],
                    [
                        409.0,
                        216.0
                    ],
                    [
                        409.0,
                        218.0
                    ],
                    [
                        410.0,
                        219.0
                    ],
                    [
                        410.0,
                        222.0
                    ],
                    [
                        411.0,
                        223.0
                    ],
                    [
                        411.0,
                        226.0
                    ],
                    [
                        412.0,
                        227.0
                    ],
                    [
                        412.0,
                        228.0
                    ],
                    [
                        413.0,
                        229.0
                    ],
                    [
                        420.0,
                        229.0
                    ],
                    [
                        421.0,
                        230.0
                    ],
                    [
                        432.0,
                        230.0
                    ],
                    [
                        433.0,
                        229.0
                    ],
                    [
                        450.0,
                        229.0
                    ],
                    [
                        451.0,
                        230.0
                    ],
                    [
                        452.0,
                        230.0
                    ],
                    [
                        453.0,
                        229.0
                    ],
                    [
                        460.0,
                        229.0
                    ],
                    [
                        461.0,
                        228.0
                    ],
                    [
                        461.0,
                        224.0
                    ],
                    [
                        462.0,
                        223.0
                    ],
                    [
                        462.0,
                        221.0
                    ],
                    [
                        464.0,
                        219.0
                    ],
                    [
                        464.0,
                        212.0
                    ],
                    [
                        465.0,
                        211.0
                    ],
                    [
                        465.0,
                        198.0
                    ],
                    [
                        466.0,
                        197.0
                    ],
                    [
                        466.0,
                        196.0
                    ],
                    [
                        465.0,
                        195.0
                    ],
                    [
                        465.0,
                        191.0
                    ],
                    [
                        463.0,
                        189.0
                    ],
                    [
                        463.0,
                        188.0
                    ],
                    [
                        462.0,
                        187.0
                    ],
                    [
                        462.0,
                        186.0
                    ],
                    [
                        459.0,
                        183.0
                    ],
                    [
                        459.0,
                        182.0
                    ],
                    [
                        457.0,
                        180.0
                    ],
                    [
                        456.0,
                        180.0
                    ],
                    [
                        454.0,
                        178.0
                    ],
                    [
                        454.0,
                        176.0
                    ],
                    [
                        453.0,
                        175.0
                    ],
                    [
                        452.0,
                        175.0
                    ],
                    [
                        450.0,
                        173.0
                    ],
                    [
                        450.0,
                        170.0
                    ],
                    [
                        449.0,
                        169.0
                    ],
                    [
                        449.0,
                        165.0
                    ],
                    [
                        448.0,
                        164.0
                    ],
                    [
                        448.0,
                        157.0
                    ],
                    [
                        447.0,
                        156.0
                    ],
                    [
                        447.0,
                        155.0
                    ],
                    [
                        446.0,
                        154.0
                    ],
                    [
                        446.0,
                        153.0
                    ],
                    [
                        445.0,
                        152.0
                    ],
                    [
                        445.0,
                        150.0
                    ],
                    [
                        444.0,
                        149.0
                    ],
                    [
                        444.0,
                        146.0
                    ],
                    [
                        443.0,
                        145.0
                    ],
                    [
                        443.0,
                        144.0
                    ],
                    [
                        442.0,
                        143.0
                    ],
                    [
                        442.0,
                        142.0
                    ],
                    [
                        443.0,
                        141.0
                    ],
                    [
                        440.0,
                        138.0
                    ],
                    [
                        440.0,
                        136.0
                    ],
                    [
                        439.0,
                        135.0
                    ],
                    [
                        439.0,
                        131.0
                    ],
                    [
                        438.0,
                        130.0
                    ],
                    [
                        437.0,
                        130.0
                    ],
                    [
                        435.0,
                        128.0
                    ],
                    [
                        435.0,
                        127.0
                    ],
                    [
                        434.0,
                        126.0
                    ],
                    [
                        434.0,
                        123.0
                    ],
                    [
                        433.0,
                        122.0
                    ],
                    [
                        433.0,
                        121.0
                    ],
                    [
                        432.0,
                        120.0
                    ],
                    [
                        431.0,
                        120.0
                    ],
                    [
                        429.0,
                        118.0
                    ],
                    [
                        429.0,
                        116.0
                    ],
                    [
                        428.0,
                        115.0
                    ],
                    [
                        428.0,
                        111.0
                    ],
                    [
                        426.0,
                        111.0
                    ],
                    [
                        423.0,
                        108.0
                    ],
                    [
                        423.0,
                        98.0
                    ],
                    [
                        422.0,
                        98.0
                    ],
                    [
                        421.0,
                        99.0
                    ],
                    [
                        420.0,
                        98.0
                    ],
                    [
                        420.0,
                        91.0
                    ],
                    [
                        419.0,
                        90.0
                    ],
                    [
                        419.0,
                        84.0
                    ],
                    [
                        418.0,
                        83.0
                    ],
                    [
                        418.0,
                        80.0
                    ],
                    [
                        417.0,
                        80.0
                    ],
                    [
                        415.0,
                        78.0
                    ],
                    [
                        415.0,
                        77.0
                    ],
                    [
                        414.0,
                        76.0
                    ],
                    [
                        414.0,
                        75.0
                    ],
                    [
                        413.0,
                        74.0
                    ],
                    [
                        413.0,
                        71.0
                    ],
                    [
                        412.0,
                        71.0
                    ],
                    [
                        411.0,
                        70.0
                    ],
                    [
                        410.0,
                        70.0
                    ],
                    [
                        409.0,
                        69.0
                    ],
                    [
                        409.0,
                        67.0
                    ],
                    [
                        408.0,
                        66.0
                    ],
                    [
                        408.0,
                        65.0
                    ],
                    [
                        405.0,
                        65.0
                    ],
                    [
                        404.0,
                        64.0
                    ],
                    [
                        400.0,
                        64.0
                    ]
                ]
            ]
        }
    ]
}